sessiongpt/__init__.py
sessiongpt/main.py
sessiongpt-0.1.1.dist-info/METADATA
sessiongpt-0.1.1.dist-info/WHEEL
sessiongpt-0.1.1.dist-info/entry_points.txt
sessiongpt-0.1.1.dist-info/RECORD
