Metadata-Version: 2.1
Name: sessiongpt
Version: 0.1.1
Summary: Generates an AWS IAM session policy given a description of the tasks the user needs to perform.
Author-email: Kamil Wilk <github@kamilwilk.com>
Requires-Python: >=3.8
Requires-Dist: marvin>=2.1.5
Requires-Dist: pydantic>=2.6.2
Requires-Dist: rich>=13.7.0
Requires-Dist: typer>=0.9.0
